Workbook

Sheet Sheet1
A1: EBITA | B1: Multiple | C1: Entry Valuation | L1: Assumptions
A2: 14594000000 | B2: 8 | C2: =A2*B2 -> 116752000000 | L2: EBITA Growth Rate | M2: 0.08
L3: Interest Rate on Debt | M3: 0.08
A4: Debt% | B4: 0.65 | L4: Principal Sweep (% of EBITA, capped at debt) | M4: 0.2
A5: Debt Amonut | B5: =C2*B4 -> 75888800000 | L5: Capex (% of EBITA) | M5: 0.05
A6: Equity Amount | B6: =C2*(1-B4) -> 40863200000 | L6: Tax Rate | M6: 0.25
A8: Year | B8: EBITA | D8: Beginning Debt | E8: Interest | F8: Principal Repayment | G8: Ending Debt | H8: Capex | I8: Tax | J8: FCF
A9: 1 | B9: =A2*(1+$M$2) -> 1.576152e+10 | D9: =B5 -> 75888800000 | E9: =D9*$M$3 -> 6071104000 | F9: =MIN(B9*$M$4,D9) -> 3.152304e+09 | G9: =D9-F9 -> 72736496000 | H9: =B9*$M$5 -> 7.88076e+08 | I9: =(B9-H9-E9)*$M$6 -> 2.225585e+09 | J9: =B9-H9-E9-I9 -> 6.676755e+09
A10: 2 | B10: =B9*(1+$M$2) -> 1.7022442e+10 | D10: =G9 -> 72736496000 | E10: =D10*$M$3 -> 5818919680 | F10: =MIN(B10*$M$4,D10) -> 3.4044883e+09 | G10: =D10-F10 -> 69332007680 | H10: =B10*$M$5 -> 8.5112208e+08 | I10: =(B10-H10-E10)*$M$6 -> 2.5881e+09 | J10: =B10-H10-E10-I10 -> 7.7642999e+09
A11: 3 | B11: =B10*(1+$M$2) -> 1.8384237e+10 | D11: =G10 -> 69332007680 | E11: =D11*$M$3 -> 5.5465606e+09 | F11: =MIN(B11*$M$4,D11) -> 3.6768474e+09 | G11: =D11-F11 -> 6.565516e+10 | H11: =B11*$M$5 -> 9.1921185e+08 | I11: =(B11-H11-E11)*$M$6 -> 2.9796161e+09 | J11: =B11-H11-E11-I11 -> 8.9388484e+09
A12: 4 | B12: =B11*(1+$M$2) -> 1.9854976e+10 | D12: =G11 -> 6.565516e+10 | E12: =D12*$M$3 -> 5.2524128e+09 | F12: =MIN(B12*$M$4,D12) -> 3.9709952e+09 | G12: =D12-F12 -> 6.1684165e+10 | H12: =B12*$M$5 -> 9.9274879e+08 | I12: =(B12-H12-E12)*$M$6 -> 3.4024536e+09 | J12: =B12-H12-E12-I12 -> 1.0207361e+10
A13: 5 | B13: =B12*(1+$M$2) -> 2.1443374e+10 | D13: =G12 -> 6.1684165e+10 | E13: =D13*$M$3 -> 4.9347332e+09 | F13: =MIN(B13*$M$4,D13) -> 4.2886748e+09 | G13: =D13-F13 -> 5.739549e+10 | H13: =B13*$M$5 -> 1.0721687e+09 | I13: =(B13-H13-E13)*$M$6 -> 3.859118e+09 | J13: =B13-H13-E13-I13 -> 1.1577354e+10
A16: Exit Multiple | B16: 8 | C16: Exit Enterprise Value | D16: =B13*B16 -> 1.7154699e+11
A18: Exit Equity Value | B18: =D16-G13 -> 1.141515e+11
A20: Year | B20: 0 | C20: 1 | D20: 2 | E20: 3 | F20: 4 | G20: 5
A21: Cash Flow | B21: =-B6 -> -40863200000 | C21: 0 | D21: 0 | E21: 0 | F21: 0 | G21: =B18 -> 1.141515e+11
A23: IRR | B23: =(G21/-B21)^(1/5)-1 -> 0.22808903
A24: MOIC | B24: =B18/B6 -> 2.7935037
A27: Exit Multiple | B27: IRR | C27: MOIC
A28: 6 | B28: =((A28*$B$13-$G$13)/-$B$21)^(1/5)-1 -> 0.11765685 | C28: =(A28*$B$13-$G$13)/-$B$21 -> 1.7439837
A29: 7 | B29: =((A29*$B$13-$G$13)/-$B$21)^(1/5)-1 -> 0.178032 | C29: =(A29*$B$13-$G$13)/-$B$21 -> 2.2687437
A30: 8 | B30: =((A30*$B$13-$G$13)/-$B$21)^(1/5)-1 -> 0.22808903 | C30: =(A30*$B$13-$G$13)/-$B$21 -> 2.7935037
A31: 9 | B31: =((A31*$B$13-$G$13)/-$B$21)^(1/5)-1 -> 0.27110721 | C31: =(A31*$B$13-$G$13)/-$B$21 -> 3.3182637
A32: 10 | B32: =((A32*$B$13-$G$13)/-$B$21)^(1/5)-1 -> 0.30898483 | C32: =(A32*$B$13-$G$13)/-$B$21 -> 3.8430238

Sheet Sheet2
A1: Accquier Net income | B1: 61271000000 | D1: Deal Financing & Synergy Assumptions
A2: Accquier Shares | B2: 7608000000 | D2: Cash % | E2: 1
A3: Accquier EPS | B3: =B1/B2 -> 8.0534963 | D3: Stock % | E3: 0
D4: Debt % | E4: 0
A5: Target Net Income | B5: 10000000000 | D5: Check (Cash%+Stock%+Debt%, should = 100%) | E5: =E2+E3+E4 -> 1
A6: Target Shares | B6: 785000000 | D6: Interest Rate on New Debt | E6: 0.06
A7: Target EPS | B7: =B5/B6 -> 12.738854 | D7: Foregone Interest Rate on Cash Used | E7: 0.03
A8: Target Purchase Price | B8: 68700000000 | D8: Pre-Tax Annual Synergies | E8: 5000000000
A9: Acquier Share Price | B9: 301 | D9: Tax Rate | E9: 0.25
A10: New Shares Issused | B10: =(B8*$E$3)/B9 -> 0 | D10: Transaction Fees (% of Deal Value, one-time) | E10: 0.02
A12: Pro Forma Net Income | B12: =B1+B5+B20-B21-B22 -> 73475250000
A13: Pro Forma Shares | B13: =B2+B10 -> 7608000000
A14: Pro Forma EPS | B14: =B12/B13 -> 9.6576301
A16: Accretive/Dilutive? | B16: =IF(B14>B3,"Accretive","Dilutive") -> Accretive
A18: Cash Used | B18: =B8*$E$2 -> 68700000000
A19: Debt Raised | B19: =B8*$E$4 -> 0
A20: After-Tax Synergies | B20: =$E$8*(1-$E$9) -> 3750000000
A21: After-Tax Interest Expense on New Debt | B21: =B19*$E$6*(1-$E$9) -> 0
A22: After-Tax Foregone Interest on Cash Used | B22: =B18*$E$7*(1-$E$9) -> 1545750000
A23: Accretion / (Dilution) % | B23: =(B14-B3)/B3 -> 0.19918477
A25: One-Time Items (excluded from run-rate accretion/dilution above)
A26: Transaction Fees (Pre-Tax) | B26: =B8*$E$10 -> 1374000000
A27: Transaction Fees (After-Tax) | B27: =B26*(1-$E$9) -> 1030500000
A30: Sensitivity: Accretion/(Dilution) % vs. Pre-Tax Synergies
A31: Pre-Tax Synergies | B31: Accretion/(Dilution) %
A32: 0 | B32: =((B1+B5+A32*(1-$E$9)-$B$21-$B$22)/$B$13-$B$3)/$B$3 -> 0.13798126
A33: 2500000000 | B33: =((B1+B5+A33*(1-$E$9)-$B$21-$B$22)/$B$13-$B$3)/$B$3 -> 0.16858302
A34: 5000000000 | B34: =((B1+B5+A34*(1-$E$9)-$B$21-$B$22)/$B$13-$B$3)/$B$3 -> 0.19918477
A35: 7500000000 | B35: =((B1+B5+A35*(1-$E$9)-$B$21-$B$22)/$B$13-$B$3)/$B$3 -> 0.22978652
A36: 10000000000 | B36: =((B1+B5+A36*(1-$E$9)-$B$21-$B$22)/$B$13-$B$3)/$B$3 -> 0.26038828

Sheet Sheet3
A1: Deal Summary Dashboard
A3: LBO Summary
A4: Entry Multiple | B4: =Sheet1!B2 -> 8
A5: Exit Multiple | B5: =Sheet1!B16 -> 8
A6: IRR | B6: =Sheet1!B23 -> 0.22808903
A7: MOIC | B7: =Sheet1!B24 -> 2.7935037
A9: M&A Summary
A10: Deal Value | B10: =Sheet2!B8 -> 68700000000
A11: Financing Mix (Cash / Stock / Debt) | B11: =Sheet2!E2 -> 1 | C11: =Sheet2!E3 -> 0 | D11: =Sheet2!E4 -> 0
A12: Accretion / (Dilution) % | B12: =Sheet2!B23 -> 0.19918477
